youtube_transcript/__init__.py
youtube_transcript/cli.py
youtube_transcript/api/__init__.py
youtube_transcript/api/app.py
youtube_transcript/api/endpoints.py
youtube_transcript/api/models.py
youtube_transcript/api/web_routes.py
youtube_transcript/cache/__init__.py
youtube_transcript/config/__init__.py
youtube_transcript/config/proxy_config.py
youtube_transcript/models/__init__.py
youtube_transcript/models/database.py
youtube_transcript/models/transcript.py
youtube_transcript/repository/__init__.py
youtube_transcript/services/__init__.py
youtube_transcript/services/cache.py
youtube_transcript/services/fetcher.py
youtube_transcript/services/orchestrator.py
youtube_transcript/services/repository.py
youtube_transcript/static/css/main.css
youtube_transcript/templates/base.html
youtube_transcript/templates/error.html
youtube_transcript/templates/index.html
youtube_transcript/templates/results.html
youtube_transcript/templates/partials/error_fragment.html
youtube_transcript/templates/partials/loading.html
youtube_transcript/templates/partials/transcript_fragment.html
youtube_transcript/utils/__init__.py
youtube_transcript/utils/url_parser.py
youtube_transcript_tools-0.1.0.dist-info/METADATA
youtube_transcript_tools-0.1.0.dist-info/WHEEL
youtube_transcript_tools-0.1.0.dist-info/entry_points.txt
youtube_transcript_tools-0.1.0.dist-info/licenses/LICENSE
youtube_transcript_tools-0.1.0.dist-info/RECORD
