Metadata-Version: 2.4
Name: youtube-transcript-tools
Version: 0.1.0
Summary: A tool to fetch YouTube video transcripts via Web UI and CLI
Project-URL: Homepage, https://github.com/nilukush/youtube-transcript
Project-URL: Documentation, https://github.com/nilukush/youtube-transcript#readme
Project-URL: Repository, https://github.com/nilukush/youtube-transcript.git
Project-URL: Issues, https://github.com/nilukush/youtube-transcript/issues
Author-email: Nilesh Kumar <nilukush@gmail.com>
License: MIT
License-File: LICENSE
Keywords: api,cli,fastapi,transcript,youtube
Classifier: Development Status :: 4 - Beta
Classifier: Intended Audience :: Developers
Classifier: Intended Audience :: End Users/Desktop
Classifier: License :: OSI Approved :: MIT License
Classifier: Operating System :: OS Independent
Classifier: Programming Language :: Python :: 3
Classifier: Programming Language :: Python :: 3.10
Classifier: Programming Language :: Python :: 3.11
Classifier: Programming Language :: Python :: 3.12
Classifier: Programming Language :: Python :: 3.13
Classifier: Programming Language :: Python :: 3.14
Classifier: Topic :: Internet :: WWW/HTTP
Classifier: Topic :: Software Development :: Libraries :: Python Modules
Classifier: Topic :: Utilities
Requires-Python: >=3.10
Requires-Dist: fastapi>=0.115.0
Requires-Dist: jinja2>=3.1.0
Requires-Dist: python-multipart>=0.0.9
Requires-Dist: redis>=5.0.0
Requires-Dist: rich>=13.0.0
Requires-Dist: sqlmodel>=0.0.22
Requires-Dist: typer>=0.12.0
Requires-Dist: uvicorn[standard]>=0.30.0
Requires-Dist: youtube-transcript-api>=0.6.0
Provides-Extra: dev
Requires-Dist: black>=24.0.0; extra == 'dev'
Requires-Dist: fakeredis>=2.23.0; extra == 'dev'
Requires-Dist: mypy>=1.9.0; extra == 'dev'
Requires-Dist: pytest-asyncio>=0.24.0; extra == 'dev'
Requires-Dist: pytest-cov>=5.0.0; extra == 'dev'
Requires-Dist: pytest>=8.0.0; extra == 'dev'
Requires-Dist: responses>=0.25.0; extra == 'dev'
Requires-Dist: ruff>=0.6.0; extra == 'dev'
Requires-Dist: types-redis>=4.6.0; extra == 'dev'
